parcake-0.4.1.dist-info/METADATA
parcake-0.4.1.dist-info/WHEEL
parcake/__init__.py
parcake/grouper.py
parcake/reader.py
parcake/saver.py
parcake/sorter.py
parcake/py.typed
parcake-0.4.1.dist-info/RECORD
