Metadata-Version: 2.1
Name: parcake
Version: 0.4.1
Summary: Makes Parquet workflows a piece of cake to slice, save, and serve.
Keywords: parquet,pyarrow,pandas,chunked io,piece,parcake
Author-Email: Filipi Nascimento Silva <filipinascimento@gmail.com>
License: MIT
Classifier: Programming Language :: Python :: 3
Classifier: Programming Language :: Python :: 3.10
Classifier: License :: OSI Approved :: MIT License
Classifier: Intended Audience :: Developers
Classifier: Topic :: Software Development :: Libraries :: Python Modules
Project-URL: Homepage, https://github.com/filipinascimento/parcake
Requires-Python: >=3.9
Requires-Dist: pandas>=1.5
Requires-Dist: pyarrow>=10.0
Provides-Extra: duckdb
Requires-Dist: duckdb>=0.9; extra == "duckdb"
Provides-Extra: dev
Requires-Dist: pytest>=7.0; extra == "dev"
Requires-Dist: mypy>=1.5; extra == "dev"
Requires-Dist: ruff>=0.1.9; extra == "dev"
Requires-Dist: build>=1.0; extra == "dev"
Requires-Dist: mkdocs>=1.5; extra == "dev"
Requires-Dist: mkdocs-material>=9.5; extra == "dev"
Requires-Dist: mkdocstrings[python]>=0.24; extra == "dev"
Requires-Dist: pymdown-extensions>=10.0; extra == "dev"
Provides-Extra: docs
Requires-Dist: mkdocs>=1.5; extra == "docs"
Requires-Dist: mkdocs-material>=9.5; extra == "docs"
Requires-Dist: mkdocstrings[python]>=0.24; extra == "docs"
Requires-Dist: pymdown-extensions>=10.0; extra == "docs"
